engr/__init__.py
engr-0.1.dist-info/METADATA
engr-0.1.dist-info/RECORD
engr-0.1.dist-info/WHEEL
engr-0.1.dist-info/top_level.txt
