Metadata-Version: 2.1
Name: engr
Version: 0.1
Summary: Equations, tools, and explanations for all types of engineering.
Home-page: https://github.com/mjpierce7590/engr
Author: Michael Pierce
Author-email: michael.j.pierce@outlook.com
License: GPL
Platform: UNKNOWN
